odoo8_addon_l10n_it_account-8.0.1.1.0-nspkg.pth
odoo_addons/l10n_it_account/README.rst
odoo_addons/l10n_it_account/__init__.py
odoo_addons/l10n_it_account/__openerp__.py
odoo_addons/l10n_it_account/i18n/it.po
odoo_addons/l10n_it_account/i18n/l10n_it_account.pot
odoo_addons/l10n_it_account/i18n/sl.po
odoo_addons/l10n_it_account/models/__init__.py
odoo_addons/l10n_it_account/models/account.py
odoo_addons/l10n_it_account/models/account_tax.py
odoo_addons/l10n_it_account/models/res_config.py
odoo_addons/l10n_it_account/reports/account_reports_view.xml
odoo_addons/l10n_it_account/static/description/icon.png
odoo_addons/l10n_it_account/tests/__init__.py
odoo_addons/l10n_it_account/tests/test_account.py
odoo_addons/l10n_it_account/tools/__init__.py
odoo_addons/l10n_it_account/tools/account_tools.py
odoo_addons/l10n_it_account/views/account_view.xml
odoo_addons/l10n_it_account/views/config_view.xml
odoo8_addon_l10n_it_account-8.0.1.1.0.dist-info/METADATA
odoo8_addon_l10n_it_account-8.0.1.1.0.dist-info/WHEEL
odoo8_addon_l10n_it_account-8.0.1.1.0.dist-info/namespace_packages.txt
odoo8_addon_l10n_it_account-8.0.1.1.0.dist-info/top_level.txt
odoo8_addon_l10n_it_account-8.0.1.1.0.dist-info/RECORD
