Metadata-Version: 2.1
Name: odoo8-addon-l10n-it-account
Version: 8.0.1.1.0
Summary: Italian Localization - Account
Home-page: http://www.odoo-italia.org
Author: Agile Business Group,Abstract,Odoo Community Association (OCA)
Author-email: support@odoo-community.org
License: AGPL-3
Platform: UNKNOWN
Classifier: Programming Language :: Python
Classifier: Framework :: Odoo
Classifier: License :: OSI Approved :: GNU Affero General Public License v3
Requires-Python: ~=2.7
Requires-Dist: odoo8-addon-l10n-it-base
Requires-Dist: odoo8-addon-l10n-it-fiscalcode
Requires-Dist: odoo (<9.0a,>=8.0a)
